{"cameraMode":{"drawMode":0,"name":"Shaded","section":"Shading Mode"},"sceneLighting":false,"audioPlay":false,"sceneViewState":{"m_AlwaysRefresh":false,"showFog":true,"showSkybox":false,"showFlares":true,"showImageEffects":true,"showParticleSystems":true,"showVisualEffectGraphs":true,"m_FxEnabled":true},"in2DMode":false,"pivot":{"x":-1.4050002098083497,"y":1.2146965265274048,"z":-75.0},"rotation":{"x":-0.0006676401244476438,"y":0.8293930888175964,"z":-0.5587047338485718,"w":-0.0009975607972592116},"size":1.5763301849365235,"orthographic":false}