{"cameraMode":{"drawMode":0,"name":"Shaded","section":"Shading Mode"},"sceneLighting":false,"audioPlay":false,"sceneViewState":{"m_AlwaysRefresh":false,"showFog":true,"showSkybox":false,"showFlares":true,"showImageEffects":true,"showParticleSystems":true,"showVisualEffectGraphs":true,"m_FxEnabled":true},"in2DMode":false,"pivot":{"x":-0.0016832351684570313,"y":0.3561563491821289,"z":-0.004434213042259216},"rotation":{"x":0.0053291539661586288,"y":0.7396320104598999,"z":-0.673060953617096,"w":0.005695574916899204},"size":4.7743449211120609,"orthographic":false}